sr_vulkan_model_realesrgan/__init__.py
sr_vulkan_model_realesrgan/hook-sr_vulkan_model_realesrgan.py
sr_vulkan_model_realesrgan/models/REALESRGAN_ANIMAVIDEOV3_UP2X.bin
sr_vulkan_model_realesrgan/models/REALESRGAN_ANIMAVIDEOV3_UP2X.param
sr_vulkan_model_realesrgan/models/REALESRGAN_ANIMAVIDEOV3_UP3X.bin
sr_vulkan_model_realesrgan/models/REALESRGAN_ANIMAVIDEOV3_UP3X.param
sr_vulkan_model_realesrgan/models/REALESRGAN_ANIMAVIDEOV3_UP4X.bin
sr_vulkan_model_realesrgan/models/REALESRGAN_ANIMAVIDEOV3_UP4X.param
sr_vulkan_model_realesrgan/models/REALESRGAN_X4PLUSANIME_UP4X.bin
sr_vulkan_model_realesrgan/models/REALESRGAN_X4PLUSANIME_UP4X.param
sr_vulkan_model_realesrgan/models/REALESRGAN_X4PLUS_UP4X.bin
sr_vulkan_model_realesrgan/models/REALESRGAN_X4PLUS_UP4X.param
sr_vulkan_model_realesrgan-1.0.1.dist-info/METADATA
sr_vulkan_model_realesrgan-1.0.1.dist-info/WHEEL
sr_vulkan_model_realesrgan-1.0.1.dist-info/entry_points.txt
sr_vulkan_model_realesrgan-1.0.1.dist-info/top_level.txt
sr_vulkan_model_realesrgan-1.0.1.dist-info/RECORD
